civyk_repoix/__init__.py
civyk_repoix/cli.cp313-win_amd64.pyd
civyk_repoix/cli_tools.cp313-win_amd64.pyd
civyk_repoix/config.cp313-win_amd64.pyd
civyk_repoix/exceptions.cp313-win_amd64.pyd
civyk_repoix/logging_setup.cp313-win_amd64.pyd
civyk_repoix/mcp_responses.cp313-win_amd64.pyd
civyk_repoix/mcp_server.cp313-win_amd64.pyd
civyk_repoix/py.typed
civyk_repoix/service.cp313-win_amd64.pyd
civyk_repoix/tool_descriptions.cp313-win_amd64.pyd
civyk_repoix/tool_handlers.cp313-win_amd64.pyd
civyk_repoix/tool_schemas.cp313-win_amd64.pyd
civyk_repoix/daemon/__init__.py
civyk_repoix/daemon/manager.cp313-win_amd64.pyd
civyk_repoix/daemon/shim.cp313-win_amd64.pyd
civyk_repoix/daemon/worker.cp313-win_amd64.pyd
civyk_repoix/engines/__init__.py
civyk_repoix/engines/languages.cp313-win_amd64.pyd
civyk_repoix/engines/treesitter.cp313-win_amd64.pyd
civyk_repoix/models/__init__.py
civyk_repoix/models/ai_understanding.cp313-win_amd64.pyd
civyk_repoix/models/component.cp313-win_amd64.pyd
civyk_repoix/models/edge.cp313-win_amd64.pyd
civyk_repoix/models/file.cp313-win_amd64.pyd
civyk_repoix/models/manifest.cp313-win_amd64.pyd
civyk_repoix/models/status.cp313-win_amd64.pyd
civyk_repoix/models/symbol.cp313-win_amd64.pyd
civyk_repoix/monitors/__init__.py
civyk_repoix/monitors/file_watcher.cp313-win_amd64.pyd
civyk_repoix/monitors/git_watcher.cp313-win_amd64.pyd
civyk_repoix/monitors/parent_watcher.cp313-win_amd64.pyd
civyk_repoix/security/__init__.py
civyk_repoix/security/scanner.cp313-win_amd64.pyd
civyk_repoix/setup/__init__.py
civyk_repoix/setup/config.cp313-win_amd64.pyd
civyk_repoix/setup/mcp_setup.cp313-win_amd64.pyd
civyk_repoix/storage/__init__.py
civyk_repoix/storage/cache.cp313-win_amd64.pyd
civyk_repoix/storage/database.cp313-win_amd64.pyd
civyk_repoix/storage/repository.cp313-win_amd64.pyd
civyk_repoix/transport/__init__.py
civyk_repoix/transport/protocol.cp313-win_amd64.pyd
civyk_repoix/transport/socket.cp313-win_amd64.pyd
civyk_repoix/utils/__init__.py
civyk_repoix-1.1.0.dist-info/licenses/LICENSE
civyk_repoix-1.1.0.dist-info/METADATA
civyk_repoix-1.1.0.dist-info/WHEEL
civyk_repoix-1.1.0.dist-info/entry_points.txt
civyk_repoix-1.1.0.dist-info/top_level.txt
civyk_repoix-1.1.0.dist-info/RECORD
