Metadata-Version: 2.4
Name: civyk-repoix
Version: 1.1.0
Summary: Civyk Repo Index - Codebase indexing service for AI coding agents
Author: Civyk
License: Proprietary
Project-URL: Homepage, https://github.com/civyk/civyk-repoix
Project-URL: Documentation, https://github.com/civyk/civyk-repoix#readme
Project-URL: Repository, https://github.com/civyk/civyk-repoix
Project-URL: Issues, https://github.com/civyk/civyk-repoix/issues
Keywords: mcp,codebase,indexing,ai,coding-agents
Classifier: Development Status :: 4 - Beta
Classifier: Intended Audience :: Developers
Classifier: License :: Other/Proprietary License
Classifier: Operating System :: OS Independent
Classifier: Programming Language :: Python :: 3
Classifier: Programming Language :: Python :: 3.10
Classifier: Programming Language :: Python :: 3.11
Classifier: Programming Language :: Python :: 3.12
Classifier: Programming Language :: C
Classifier: Topic :: Software Development :: Libraries :: Python Modules
Requires-Python: >=3.10
License-File: LICENSE
Requires-Dist: pathspec>=0.12.0
Requires-Dist: tree-sitter>=0.21.0
Requires-Dist: tree-sitter-python>=0.21.0
Requires-Dist: tree-sitter-javascript>=0.21.0
Requires-Dist: tree-sitter-typescript>=0.21.0
Requires-Dist: tree-sitter-java>=0.21.0
Requires-Dist: tree-sitter-go>=0.21.0
Requires-Dist: tree-sitter-c-sharp>=0.21.0
Requires-Dist: tree-sitter-rust>=0.21.0
Requires-Dist: tree-sitter-ruby>=0.21.0
Requires-Dist: tree-sitter-php>=0.23.0
Requires-Dist: tree-sitter-sql>=0.3.0
Requires-Dist: tree-sitter-markdown>=0.3.0
Requires-Dist: tree-sitter-json>=0.24.0
Requires-Dist: tree-sitter-yaml>=0.6.0
Requires-Dist: tree-sitter-toml>=0.6.0
Requires-Dist: tree-sitter-xml>=0.6.0
Requires-Dist: watchdog>=4.0.0
Requires-Dist: aiosqlite>=0.19.0
Requires-Dist: mcp>=1.0.0
Requires-Dist: pyyaml>=6.0
Requires-Dist: gitpython>=3.1.0
Requires-Dist: pydantic>=2.0.0
Provides-Extra: dev
Requires-Dist: pytest>=8.0.0; extra == "dev"
Requires-Dist: pytest-asyncio>=0.23.0; extra == "dev"
Requires-Dist: pytest-benchmark>=4.0.0; extra == "dev"
Requires-Dist: pytest-cov>=4.0.0; extra == "dev"
Requires-Dist: mypy>=1.8.0; extra == "dev"
Requires-Dist: ruff>=0.4.0; extra == "dev"
Requires-Dist: types-PyYAML>=6.0.0; extra == "dev"
Requires-Dist: pyinstaller>=6.0.0; extra == "dev"
Requires-Dist: debugpy>=1.8.0; extra == "dev"
Requires-Dist: nuitka>=2.0.0; extra == "dev"
Requires-Dist: ordered-set>=4.1.0; extra == "dev"
Dynamic: license-file
